mycalc/calculator.py
mycalc/calculatorr.py
hwKim0524-0.0.2.dist-info/METADATA
hwKim0524-0.0.2.dist-info/WHEEL
hwKim0524-0.0.2.dist-info/top_level.txt
hwKim0524-0.0.2.dist-info/RECORD
