Metadata-Version: 2.1
Name: hwKim0524
Version: 0.0.2
Summary: nice calcurator
Home-page: 
Download-URL: 
Author: hwKim
License: UNKNOWN
Platform: UNKNOWN
Classifier: Programming Language :: Python :: 3
